odoo/addons/easy_my_coop_taxshelter_report/README.rst
odoo/addons/easy_my_coop_taxshelter_report/__init__.py
odoo/addons/easy_my_coop_taxshelter_report/__manifest__.py
odoo/addons/easy_my_coop_taxshelter_report/data/mail_template_data.xml
odoo/addons/easy_my_coop_taxshelter_report/data/scheduler_data.xml
odoo/addons/easy_my_coop_taxshelter_report/demo/tax_shelter_demo.xml
odoo/addons/easy_my_coop_taxshelter_report/i18n/easy_my_coop_taxshelter_report.pot
odoo/addons/easy_my_coop_taxshelter_report/i18n/fr_BE.po
odoo/addons/easy_my_coop_taxshelter_report/models/__init__.py
odoo/addons/easy_my_coop_taxshelter_report/models/mail_template.py
odoo/addons/easy_my_coop_taxshelter_report/models/tax_shelter_declaration.py
odoo/addons/easy_my_coop_taxshelter_report/readme/CONTRIBUTORS.rst
odoo/addons/easy_my_coop_taxshelter_report/readme/DESCRIPTION.rst
odoo/addons/easy_my_coop_taxshelter_report/readme/DEVELOP.rst
odoo/addons/easy_my_coop_taxshelter_report/reports/tax_shelter_report.xml
odoo/addons/easy_my_coop_taxshelter_report/reports/tax_shelter_resold_report.xml
odoo/addons/easy_my_coop_taxshelter_report/reports/tax_shelter_shares_report.xml
odoo/addons/easy_my_coop_taxshelter_report/reports/tax_shelter_subscription_report.xml
odoo/addons/easy_my_coop_taxshelter_report/security/ir.model.access.csv
odoo/addons/easy_my_coop_taxshelter_report/static/description/index.html
odoo/addons/easy_my_coop_taxshelter_report/tests/tests.txt
odoo/addons/easy_my_coop_taxshelter_report/views/tax_shelter_declaration_view.xml
odoo12_addon_easy_my_coop_taxshelter_report-12.0.1.0.1.99.dev29.dist-info/METADATA
odoo12_addon_easy_my_coop_taxshelter_report-12.0.1.0.1.99.dev29.dist-info/WHEEL
odoo12_addon_easy_my_coop_taxshelter_report-12.0.1.0.1.99.dev29.dist-info/top_level.txt
odoo12_addon_easy_my_coop_taxshelter_report-12.0.1.0.1.99.dev29.dist-info/RECORD
